veinmind/__init__.py
veinmind/binding.py
veinmind/command.py
veinmind/container.py
veinmind/containerd.py
veinmind/docker.py
veinmind/filesystem.py
veinmind/iac.py
veinmind/image.py
veinmind/log.py
veinmind/process.py
veinmind/remote.py
veinmind/runtime.py
veinmind/service.py
veinmind/structseq.py
veinmind/tarball.py
veinmind-1.5.1.dist-info/METADATA
veinmind-1.5.1.dist-info/WHEEL
veinmind-1.5.1.dist-info/top_level.txt
veinmind-1.5.1.dist-info/RECORD
