Metadata-Version: 2.1
Name: veinmind
Version: 1.5.1
Summary: libVeinMind API python binding
Home-page: https://github.com/chaitin/libveinmind
Author: Haoran Luo
Author-email: haoran.luo@chaitin.com
License: UNKNOWN
Project-URL: Bug Tracker, https://github.com/chaitin/libveinmind/issues
Platform: UNKNOWN
Classifier: Programming Language :: Python :: 3
Classifier: License :: Free To Use But Restricted
Classifier: Operating System :: POSIX :: Linux
Requires-Python: >=3.3
Requires-Dist: click (==7.1.2)
